{
    "Date": "2024-01-20",
    "Theme": "Reflecting on Creation",
    "day": 1,
    "Scripture": "Genesis 1:1-13",
    "startRef": "GEN.1.1",
    "endRef": "GEN.1.13",
    "Devotion": "Today, ponder the majestic account of God's creation. Consider the power and intentionality with which God brought forth light, separated the waters, and formed the foundations of the earth. As you read, marvel at the Creator's design and order in the universe.",
    "PrayerPrompt": "Pray for a renewed appreciation of God's creative power in your life.",
    "ImageDescription": "An image depicting the beauty of the created world, with vibrant landscapes, oceans, and celestial bodies.",
    "OptionalPassages": ["Psalm 104", "Proverbs 3:19-20"],
    "Quotation": {
      "Quote": "In the beginning, God created the heavens and the earth.",
      "Author": "Genesis 1:1",
      "Link": "https://www.biblegateway.com/passage/?search=Genesis+1:1"
    }
  }